COPYING
NEWS
setup.cfg
setup.py
LinkExchange.Django.egg-info/PKG-INFO
LinkExchange.Django.egg-info/SOURCES.txt
LinkExchange.Django.egg-info/dependency_links.txt
LinkExchange.Django.egg-info/entry_points.txt
LinkExchange.Django.egg-info/requires.txt
LinkExchange.Django.egg-info/top_level.txt
linkexchange_django/__init__.py
linkexchange_django/context_processors.py
linkexchange_django/db_drivers.py
linkexchange_django/models.py
linkexchange_django/support.py
linkexchange_django/tests.py
linkexchange_django/views.py
linkexchange_django/management/__init__.py
linkexchange_django/management/commands/__init__.py
linkexchange_django/management/commands/lxrefresh.py
linkexchange_django/templatetags/__init__.py
linkexchange_django/templatetags/linkexchange_tags.py
tests/__init__.py
tests/test_django.py